pymess/residual.py
pymess/__init__.py
pymess/misc.py
pymess/_c_interface.cpython-39-x86_64-linux-gnu.so
pymess/direct_select.py
pymess/options.py
pymess/dense_nm_gmpare.py
pymess/status.py
pymess/equation.py
pymess/enum.py
pymess/lradi.py
pymess/lrnm.py
pymess/easy.py
pymess/glyap3.py
pymess/equations/std.py
pymess/equations/__init__.py
pymess/equations/dae2.py
pymess/equations/dae1.py
pymess/equations/so2.py
pymess/equations/so1.py
pymess/.libs/libmess_python_3.9.so
pymess-1.0.0.data/data/COPYING
pymess.libs/libz-d8a329de.so.1.2.7
pymess.libs/libsuperlu-bcda16a7.so.5.1.1
pymess.libs/libcamd-e23033c0.so.2.4.6
pymess.libs/libopenblasp-r0-b7b0ae65.3.11.so
pymess.libs/libmetis-9d5c57f1.so
pymess.libs/libcholmod-64c54181.so.3.0.12
pymess.libs/libarpack-08d866f1.so.2.0.0
pymess.libs/libbz2-a273e504.so.1.0.6
pymess.libs/libgomp-a34b3233.so.1.0.0
pymess.libs/liblzma-07b5b5c8.so.5.2.2
pymess.libs/libquadmath-96973f99.so.0.0.0
pymess.libs/libcxsparse-5247e20a.so.3.2.0
pymess.libs/libcolamd-22ba12a8.so.2.9.6
pymess.libs/libumfpack-896e8ccd.so.5.7.7
pymess.libs/libsuitesparseconfig-1905b8cb.so.5.3.0
pymess.libs/libccolamd-0cc34694.so.2.9.6
pymess.libs/libamd-866791fc.so.2.4.6
pymess.libs/libgfortran-040039e1.so.5.0.0
pymess-1.0.0.dist-info/RECORD
pymess-1.0.0.dist-info/WHEEL
pymess-1.0.0.dist-info/METADATA
pymess-1.0.0.dist-info/COPYING
pymess-1.0.0.dist-info/top_level.txt
