Metadata-Version: 2.1
Name: pymess
Version: 1.0.0
Summary: Python interface to the C-M.E.S.S. library
Home-page: http://www.mpg-magdeburg.mpg.de/projects/mess
Author: ['Peter Benner', 'Peter Benner, Martin Koehler', 'Maximilian Behr', 'Jens Saak', 'Nitin Prasad']
Author-email: UNKNOWN
License: GPLv2+
Keywords: Matrix Equations Py-M.E.S.S. pymess C-M.E.S.S. cmess
Platform: UNKNOWN
Classifier: Development Status :: 5 - Production/Stable
Classifier: Environment :: Console
Classifier: Intended Audience :: Education
Classifier: Intended Audience :: Science/Research
Classifier: License :: OSI Approved :: GNU General Public License v2 or later (GPLv2+)
Classifier: Natural Language :: English
Classifier: Operating System :: MacOS :: MacOS X
Classifier: Operating System :: POSIX :: Linux
Classifier: Programming Language :: C
Classifier: Programming Language :: Fortran
Classifier: Programming Language :: Python :: 2.7
Classifier: Programming Language :: Python :: 3
Classifier: Programming Language :: Python :: 3.3
Classifier: Programming Language :: Python :: 3.4
Classifier: Programming Language :: Python :: 3.5
Classifier: Programming Language :: Python :: 3.6
Classifier: Programming Language :: Python :: 3.7
Classifier: Topic :: Scientific/Engineering :: Mathematics
Requires-Dist: numpy (>=1.6.0)
Requires-Dist: scipy (>=0.16.0)
